inception_tools/__init__.py
inception_tools/archetype.py
inception_tools/archetype_base.py
inception_tools/archetype_descriptor.py
inception_tools/archetype_metadata.py
inception_tools/archetype_parameters.py
inception_tools/archetype_resource_builder.py
inception_tools/cli.py
inception_tools/constants.py
inception_tools/directory_builder.py
inception_tools/exception.py
inception_tools/file_builder.py
inception_tools/json_serializable.py
inception_tools/serializable.py
inception_tools/standard_archetype.py
inception_tools/template_archetype.py
inception_tools/template_directory_builder.py
inception_tools/template_file_builder.py
inception_tools/data/archetypes/inception-tools-archetype-cli-1.0/LICENSE.jinja
inception_tools/data/archetypes/inception-tools-archetype-cli-1.0/Makefile.jinja
inception_tools/data/archetypes/inception-tools-archetype-cli-1.0/Pipfile.jinja
inception_tools/data/archetypes/inception-tools-archetype-cli-1.0/README.rst.jinja
inception_tools/data/archetypes/inception-tools-archetype-cli-1.0/archetype-descriptor.json
inception_tools/data/archetypes/inception-tools-archetype-cli-1.0/archetype-metadata.json
inception_tools/data/archetypes/inception-tools-archetype-cli-1.0/log.cfg.jinja
inception_tools/data/archetypes/inception-tools-archetype-cli-1.0/setup.cfg.jinja
inception_tools/data/archetypes/inception-tools-archetype-cli-1.0/setup.py.jinja
inception_tools/data/archetypes/inception-tools-archetype-cli-1.0/package/__init__.py.jinja
inception_tools/data/archetypes/inception-tools-archetype-cli-1.0/package/cli.py.jinja
inception_tools/data/archetypes/inception-tools-archetype-cli-1.0/tests/__init__.py.jinja
inception_tools/data/archetypes/inception-tools-archetype-cli-1.0/tests/integration/__init__.py.jinja
inception_tools/data/archetypes/inception-tools-archetype-cli-1.0/tests/unit/__init__.py.jinja
inception_tools/data/archetypes/inception-tools-archetype-lib-1.0/LICENSE.jinja
inception_tools-0.0.8.dev20220628.dist-info/LICENSE.txt
inception_tools-0.0.8.dev20220628.dist-info/METADATA
inception_tools-0.0.8.dev20220628.dist-info/WHEEL
inception_tools-0.0.8.dev20220628.dist-info/entry_points.txt
inception_tools-0.0.8.dev20220628.dist-info/top_level.txt
inception_tools-0.0.8.dev20220628.dist-info/RECORD
