Metadata-Version: 2.1
Name: inception-tools
Version: 0.0.8.dev20220628
Summary: A lightweight package for creating Python project templates.
Home-page: https://github.com/inception-tools/inception-tools/
Author: Andrew van Herick
Author-email: avanherick@gmail.com
License: Apache Software License 2.0
Project-URL: Documentation, https://github.com/inception-tools/inception-tools/
Platform: UNKNOWN
Classifier: License :: OSI Approved :: Apache Software License
Classifier: Operating System :: OS Independent
Classifier: Programming Language :: Python :: 3 :: Only
Requires-Python: >=3.6
License-File: LICENSE.txt
Requires-Dist: click
Requires-Dist: jinja2
Requires-Dist: jsonschema
